melodiam/__init__.py
melodiam/api.py
melodiam/config.py
melodiam/datastructures.py
melodiam/model.py
melodiam/login/__init__.py
melodiam/login/api.py
melodiam/player/__init__.py
melodiam/player/api.py
melodiam/user/__init__.py
melodiam/user/api.py
melodiam/utils/__init__.py
melodiam/utils/events.py
melodiam/utils/log.py
melodiam-0.1.2.data/data/LICENSE
melodiam-0.1.2.dist-info/LICENSE
melodiam-0.1.2.dist-info/METADATA
melodiam-0.1.2.dist-info/WHEEL
melodiam-0.1.2.dist-info/top_level.txt
melodiam-0.1.2.dist-info/RECORD
